python_mcp_test/__init__.py
python_mcp_test/server.py
python_mcp_test-0.1.3.dist-info/METADATA
python_mcp_test-0.1.3.dist-info/WHEEL
python_mcp_test-0.1.3.dist-info/entry_points.txt
python_mcp_test-0.1.3.dist-info/top_level.txt
python_mcp_test-0.1.3.dist-info/RECORD
