Metadata-Version: 2.4
Name: python-mcp-test
Version: 0.1.3
Summary: Add your description here
Requires-Python: >=3.11
Requires-Dist: mcp[cli]>=1.10.1
Requires-Dist: requests>=2.32.4
Requires-Dist: python-dotenv>=1.0.0
